rancher_autobackup/__init__.py
rancher_autobackup-1.2.0.data/scripts/rancher-autobackup
rancher_autobackup-1.2.0.dist-info/DESCRIPTION.rst
rancher_autobackup-1.2.0.dist-info/METADATA
rancher_autobackup-1.2.0.dist-info/RECORD
rancher_autobackup-1.2.0.dist-info/WHEEL
rancher_autobackup-1.2.0.dist-info/metadata.json
rancher_autobackup-1.2.0.dist-info/top_level.txt
