Metadata-Version: 2.0
Name: rancher-autobackup
Version: 1.2.0
Summary: Rancher stack backups to git repository
Home-page: https://github.com/oscarsix/rancher_autobackup
Author: Oskar Malnowicz
Author-email: oscarsix@protonmail.ch
License: MIT
Platform: UNKNOWN
Requires-Python: >=3.6
Requires-Dist: requests
